logtailor/__init__.py
logtailor/logtailor.py
logtailor/processors.py
logtailor-1.2.3.dist-info/LICENSE
logtailor-1.2.3.dist-info/METADATA
logtailor-1.2.3.dist-info/WHEEL
logtailor-1.2.3.dist-info/entry_points.txt
logtailor-1.2.3.dist-info/top_level.txt
logtailor-1.2.3.dist-info/RECORD
