Metadata-Version: 2.1
Name: logtailor
Version: 1.2.3
Summary: Log tail and filter tool.
Home-page: UNKNOWN
Author: Stefan Braun
Author-email: sb@stbraun.com
License: MIT
Keywords: development tools
Platform: UNKNOWN
Classifier: Development Status :: 4 - Beta
Classifier: Intended Audience :: Developers
Classifier: License :: OSI Approved :: MIT License
Classifier: Programming Language :: Python
Classifier: Programming Language :: Python :: 3.8
Classifier: Programming Language :: Python :: 3 :: Only
Classifier: Programming Language :: Python :: Implementation :: CPython
Classifier: Topic :: Software Development :: Libraries :: Python Modules
Requires-Dist: click
Requires-Dist: confloader
Requires-Dist: loguru
Requires-Dist: pex
Requires-Dist: pytest
Requires-Dist: pytest-watch
